api_wrapper.py
setup.py
cryptakings_api.egg-info/PKG-INFO
cryptakings_api.egg-info/SOURCES.txt
cryptakings_api.egg-info/dependency_links.txt
cryptakings_api.egg-info/requires.txt
cryptakings_api.egg-info/top_level.txt