Metadata-Version: 1.0
Name: cryptakings-api
Version: 0.1
Summary: Python wrapper for REST API of CryptaKings Service
Home-page: https://github.com/vegeta1k95/CryptaKings-API-Wrapper
Author: vegeta1k95
Author-email: tunerzinc@gmail.com
License: UNKNOWN
Platform: UNKNOWN
